AUTHORS
ChangeLog
LICENSE
README.rst
requirements.txt
setup.cfg
setup.py
tox.ini
sphinxcontrib/__init__.py
sphinxcontrib/docbookrestapi/__init__.py
sphinxcontrib/docbookrestapi/docbook.py
sphinxcontrib/docbookrestapi/setup.py
sphinxcontrib/docbookrestapi/tests/__init__.py
sphinxcontrib_docbookrestapi.egg-info/PKG-INFO
sphinxcontrib_docbookrestapi.egg-info/SOURCES.txt
sphinxcontrib_docbookrestapi.egg-info/dependency_links.txt
sphinxcontrib_docbookrestapi.egg-info/namespace_packages.txt
sphinxcontrib_docbookrestapi.egg-info/not-zip-safe
sphinxcontrib_docbookrestapi.egg-info/requires.txt
sphinxcontrib_docbookrestapi.egg-info/top_level.txt